octobot_cli/__init__.py
octobot_cli/cli.py
octobot_cli/manager.py
octobot_cli/octobot_cli.py
octobot_cli/octobot_docker.py
octobot_cli/octobot_pip.py
octobot_cli/util.py
OctoBot_CLI-1.0.8.dist-info/LICENSE
OctoBot_CLI-1.0.8.dist-info/METADATA
OctoBot_CLI-1.0.8.dist-info/WHEEL
OctoBot_CLI-1.0.8.dist-info/entry_points.txt
OctoBot_CLI-1.0.8.dist-info/top_level.txt
OctoBot_CLI-1.0.8.dist-info/RECORD
